base5/__init__.py
base5/__main__.py
base5/py.typed
base5-0.5.dist-info/COPYING
base5-0.5.dist-info/METADATA
base5-0.5.dist-info/WHEEL
base5-0.5.dist-info/top_level.txt
base5-0.5.dist-info/RECORD
