Metadata-Version: 2.1
Name: base5
Version: 0.5
Summary: This is the best encryption library for Nasr
Author: base5
Classifier: Programming Language :: Python :: 3
License-File: COPYING
